LICENCE.txt
MANIFEST.in
README.rst
setup.py
djangotribune/__init__.py
djangotribune/actions.py
djangotribune/admin.py
djangotribune/assets.py
djangotribune/bak.py
djangotribune/clocks.py
djangotribune/crumbs.py
djangotribune/forms.py
djangotribune/models.py
djangotribune/parser.py
djangotribune/settings_local.py
djangotribune/tests.py
djangotribune/urls.py
djangotribune.egg-info/PKG-INFO
djangotribune.egg-info/SOURCES.txt
djangotribune.egg-info/dependency_links.txt
djangotribune.egg-info/not-zip-safe
djangotribune.egg-info/requires.txt
djangotribune.egg-info/top_level.txt
djangotribune/locale/fr/LC_MESSAGES/django.mo
djangotribune/locale/fr/LC_MESSAGES/django.po
djangotribune/management/__init__.py
djangotribune/management/commands/__init__.py
djangotribune/management/commands/tribune.py
djangotribune/migrations/0001_initial.py
djangotribune/migrations/0002_auto__chg_field_message_clock__chg_field_message_created.py
djangotribune/migrations/__init__.py
djangotribune/static/css/djangotribune/frontend.css
djangotribune/static/images/djangotribune/alert.png
djangotribune/static/images/djangotribune/spinner_arrows.gif
djangotribune/static/js/djangotribune/csrf.js
djangotribune/static/js/djangotribune/main.js
djangotribune/static/js/jquery/jquery-textrange.js
djangotribune/static/js/jquery/jquery.cookies.2.2.0.js
djangotribune/static/js/jquery/jquery.cookies.2.2.0.min.js
djangotribune/static/js/jquery/jquery.querystring.js
djangotribune/static/js/jquery/jwerty.0.3.2.9.js
djangotribune/templates/djangotribune/base.html
djangotribune/templates/djangotribune/board.html
djangotribune/templates/djangotribune/board_noscript.html
djangotribune/templates/djangotribune/help.html
djangotribune/templates/djangotribune/include_css.html
djangotribune/templates/djangotribune/include_js.html
djangotribune/templates/djangotribune/url_archives.html
djangotribune/templatetags/__init__.py
djangotribune/templatetags/tribune.py
djangotribune/test_fixtures/initial_data.json
djangotribune/views/__init__.py
djangotribune/views/archives.py
djangotribune/views/clock.py
djangotribune/views/discovery.py
djangotribune/views/help.py
djangotribune/views/post.py
djangotribune/views/remote.py