Metadata-Version: 1.1
Name: djangotribune
Version: 0.7.7
Summary: 
